[
  {
    "date": "2026-06-06",
    "timestamp": "2026-06-06T08:38:31.880569+00:00",
    "verdict": "C",
    "conviction": 2,
    "trajectory": "STABLE",
    "interrogator_score": 4,
    "transcript_source": "fmp",
    "source": "opus_regime_mod",
    "bull_thesis": "Ambu is a genuine, financially corroborated operational turnaround that the market is mistaking for a stalling story. Under CEO Britt Meelby Jensen (in the role since 2022) and CFO Henrik Skak Bender (who joined in January 2024), the company's 'ZOOM IN' transformation lifted revenue from DKK 4.78 billion in fiscal year 2023 to DKK 6.04 billion in fiscal year 2025, a three-year compound annual growth rate of 10.8%, while the EBIT margin before special items expanded from roughly 6% to 13.0%, net income tripled from DKK 168 million to DKK 609 million, and gross margin held steady at 56%.\n\nThis is a structural-growth franchise. Single-use (disposable) endoscopy is a multi-year secular shift away from reusable scopes, running at roughly 5% underlying procedure growth per year plus additional market-penetration gains on top, and Ambu is the first-mover category leader. The Endoscopy Solutions segment now accounts for 63% of revenue and continues to compound at double-digit rates — up 15.4% in fiscal year 2025 and 14.4% in the first quarter of fiscal year 2025/26 — across a broad bronchoscopy portfolio (the aScope 4/5 Broncho), an expanding urology platform (the aScope 5 Cysto and Uretero), and a genuinely new catalyst the market appears to under-appreciate: the SureSight video laryngoscope aimed at a roughly DKK 4 billion US market where video now accounts for 50% of intubations and is growing at around 20% annually. A SureSight Mobile extension was launched in the first quarter of fiscal year 2025/26 and management describes it as starting to generate meaningful revenue.\n\nThe balance sheet is a fortress: net cash of DKK 140 million, an Altman Z-score (a measure of financial health, where higher numbers indicate lower insolvency risk) of 9.5, and a Piotroski score of 6 out of 9. That gives unused capacity for acquisitions; management noted the company could lever up to 2.5 times EBITDA (earnings before interest, taxes, depreciation, and amortisation) if the right opportunity arose.\n\nManagement credibility is high. They raised the Endoscopy segment guidance mid-fiscal year 2023/24 (from 'around 15%' to 'above 15%') and delivered 19.7%. They declined to flatter free cash flow (FCF) guidance after a strong opening quarter. And CFO Bender explicitly refused to strip out currency impacts from the 20%-EBIT-margin-by-2028 target when an analyst invited him to do so: 'I don't see that. We guide EBIT margin, including FX... something we can manage.'\n\nThe constructive catalyst path runs as follows: first, operating leverage gradually closes the gap from the current 13% EBIT margin toward the 20% target; second, SureSight and the urology platform inflect growth back upward as management guides 'an acceleration in our growth levels in this segment for the coming quarters'; third, tariff and currency costs normalise as the Mexico and USMCA (United States-Mexico-Canada Agreement) manufacturing ramp proceeds on plan and a likely supportive outcome from US Section 232 trade proceedings removes what management calls a temporary cost drag, releasing the gap between reported earnings and the subdued DKK 13 million quarterly FCF; fourth, optional accretive acquisitions deploy the net-cash firepower.\n\nConditions that must hold: Endoscopy growth must re-accelerate beyond the 8.6% consolidated first-quarter figure; FCF conversion must inflect toward reported earnings, which is the central proof point; the 20% margin target must survive the tariff and currency environment without relying on the accounting tailwind from the Invendo gastrointestinal write-down; and competition from Boston Scientific, Olympus's single-use range, and Chinese entrants must not compress the first-mover premium. If those conditions hold, the current price — 21% below the 200-day moving average and near the bottom of its 52-week range — is a de-rated entry into a compounding category leader.",
    "bear_thesis": "The 'deep value' label is a category error and the current price embeds an acceleration that the cash flows flatly contradict. Ambu trades at 180.3 times trailing free cash flow with zero margin of safety (the gap between intrinsic value and price). Every valuation approach — discounted cash flow (DCF, which projects future cash flows and discounts them back to today), earnings power value, Graham number, owner earnings, and an intrinsic value estimate using a 15% discount rate — reads negative 100% margin of safety, with a DCF fair value of roughly DKK 4.90 against a market price of DKK 66. This is a premium growth-and-quality multiple, not a value price, sitting on a cash-flow base that has not grown: FCF three-year compound annual growth rate is 0.0%, FCF fell 7% year-over-year, and first-quarter fiscal year 2025/26 free cash flow was just DKK 13 million.\n\nThe earnings optics are inflated. The fiscal year 2025 headline earnings per share of DKK 2.28 (+159% year-over-year) overstates the run rate; FMP trailing-twelve-months diluted EPS is only DKK 1.78, and the most recent quarter's EPS was down 37% year-over-year. The 'tripling earnings' story is already reversing at the margin. Capital efficiency is poor for the multiple: return on invested capital of 5.9% and return on equity of 5.2% are both below a reasonable cost of capital, funding a 'global endoscopy leadership' ambition that the underlying returns do not yet justify.\n\nGrowth itself is decelerating. Consolidated organic growth has gone from 14% to 13.8% to 13.1% to 8.6% across successive reporting periods. The Anaesthesia and Patient Monitoring (A&PM) segment has rolled over to negative 0.1% as prior price-increase comparables lap and product exclusivity is lost. Management walked back fiscal year 2025/26 guidance from 11-13% to 10-13% just one month after the Capital Markets Day — a soft guide-down dressed as a wider range — and an analyst from SEB pushed back twice: 'I'm still a bit surprised... it was only one month ago.' The promised re-acceleration is forward-looking and unproven.\n\nExogenous risk is now structural rather than temporary, despite management's repeated characterisation. Unresolved US Section 232 tariffs, an open court case challenging IEEPA (International Emergency Economic Powers Act) tariffs, and a standing currency mismatch — US dollar revenue against Chinese renminbi, Malaysian ringgit, and Mexican peso cost bases — are real margin drags. The path to 20% EBIT margin must overcome all of these, and it partly leans on the roughly 0.5 percentage-point EBIT tailwind that the Invendo gastrointestinal write-down mechanically created, a point one analyst flagged directly.\n\nThe original total addressable market story has quietly contracted. The gastrointestinal leg (Duodeno and Colon) was written down, the cholangioscope was paused, and management acknowledged that gastroenterology 'takes longer to unlock than originally assumed,' with single-use penetration below 1%. The headline transitional pass-through (TPT) and CMS reimbursement catalyst was raised four times across earnings calls and quantified zero times ('difficult to exactly monitor the net effect') and is now late in its 24-to-36-month life.\n\nPositioning corroborates the bearish read: smart-money score of 9 out of 100, institutional flow at a neutral 50 out of 100, insider buy ratio of 0.00 (no insider purchases at a price 21% below the 200-day moving average), and a tape only 11% up the 52-week range. This is a clear downtrend, not a washed-out floor.\n\nWhat confirms the bear case: another quarter of sub-10% consolidated growth, FCF failing to inflect off the DKK 13 million base, an adverse Section 232 determination, or a margin guide that needs the accounting tailwind to reach 20%. There is no value-unlocking corporate catalyst — no spin-off, no activist shareholder, no buyback authorisation, no dividend, no asset sale — so a 180-times multiple on flat FCF must be paid down through time rather than re-rated upward.",
    "consensus_delta": "Where we disagree with the market: for a deep-value signal the test is normally whether the market is pricing in terminal decline on a company with stable or growing earnings power. Here the situation is the reverse. The market is pricing premium, accelerating growth — 180.3 times trailing free cash flow, zero margin of safety, every valuation model at negative 100% margin of safety, a DCF fair value of roughly DKK 4.90 against a price of DKK 66 — into a company whose cash earnings power has been flat for three years (FCF three-year compound annual growth rate of 0.0%, down 7% year-over-year, DKK 13 million in the most recent quarter) and is decelerating (consolidated organic growth falling from 14% to 8.6%; fiscal year guidance walked back from 11-13% to 10-13% one month after the Capital Markets Day).\n\nThere is no deep-value disagreement to exploit here — the mispricing runs the other way. The market's specific assumptions that appear wrong are: (a) that the fiscal year EPS of DKK 2.28 reflects run-rate earnings power — trailing-twelve-months diluted EPS is only DKK 1.78 and the most recent quarter's EPS was down 37% year-over-year, so the 'earnings tripled' framing is already reversing; (b) that the 20% EBIT-margin-by-2028 path is clean — it must now absorb structural tariff and currency drag and leans partly on the roughly 0.5 percentage-point accounting tailwind from the Invendo gastrointestinal write-down; (c) that tariff and currency costs are 'temporary' as management repeats — Section 232 is unresolved and the IEEPA court case is open; and (d) that the headline TPT and CMS reimbursement was ever a quantifiable catalyst (raised four times, quantified zero times, now late in its 24-to-36-month life).\n\nThe only genuinely under-modelled positive is SureSight — a roughly DKK 4 billion US video laryngoscope market, 50% of intubations now video, growing around 20% — but it is nowhere near large enough to justify 180 times FCF. The asymmetry, if any, favours disappointment rather than a positive re-rating surprise.",
    "forcing_function": "The catalyst that forces a re-rating is absent here, and that is the core problem for any constructive case. Ambu has no announced spin-off, no activist shareholder, no buyback authorisation, no dividend initiation, no asset sale, and is structurally a single cash-generating unit — management confirmed that goodwill is tested at the total-company level — so the classic mechanisms for unlocking value are all absent.\n\nThe only hard-dated events on the calendar are binary and macro-controlled, and they skew negative rather than toward a bullish re-rating. First, the Section 232 tariff determination, which management expects within one to two months (roughly the second quarter of 2026), alongside the parallel IEEPA tariff court case — both are out of Ambu's control. Second, the next quarterly print (second half of fiscal year 2025/26), which tests the promised growth re-acceleration and whether FCF inflects off the DKK 13 million base; this reads as a risk event rather than a positive catalyst.\n\nNeither of those hard-dated macro-binary events represents the type of positive forcing function that would justify a high-conviction entry. The favourable investment scenarios in the current market regime — structural special situations, deleveraging or distressed credits, spin-offs, forced-seller dislocations — are entirely absent here. The dated events are potential headwinds, not a window that shatters an overly pessimistic consensus.",
    "valley_of_death": "The risky window: the signal type is deep value, so the normal concern is whether a forced-selling event or macro shock kills the thesis before a margin of safety materialises. Here, however, there is no margin of safety to converge toward (zero percent), so the near-term risk is simpler — continued multiple compression while the fundamentals fail to deliver the acceleration the price requires.\n\nThe concrete three-to-nine-month hazards are as follows. First, the Section 232 tariff ruling is explicitly imminent — management said it is 'likely it will come out in the next month or maybe two' — a binary, externally controlled outcome that, if adverse to USMCA or medical technology products, directly undermines the margin glide-path. This is precisely the kind of hard-binary, macro-controlled catalyst that is considered low quality in terms of investibility: Ambu does not control the outcome.\n\nSecond, FCF is already near zero (DKK 13 million in the first quarter of fiscal year 2025/26) and management pre-warned of a capital expenditure step-up plus working-capital normalisation (accounts receivable expected to move back toward roughly 20% of rolling revenue), so reported second-half FCF could remain depressed and keep the 180-times multiple visibly unsupported.\n\nThird, the promised growth re-acceleration ('acceleration in the coming quarters') must materialise in the second half of fiscal year 2025/26. If the next print is again sub-10% consolidated growth, the de-rating extends.\n\nFourth, A&PM continues to roll over (down 0.1%, with lost exclusivity) and the US commercial team restructuring under the new leader Scott Heinzelman — shifting toward integrated delivery networks (IDNs) and group purchasing organisations (GPOs) — carries execution cost and disruption in exactly these quarters.\n\nSolvency is not the risk. There is no debt wall — the balance sheet carries net cash and an Altman Z-score of 9.5. The risk is a richly priced, decelerating compounder grinding lower as successive quarters fail to justify the multiple, with an adverse tariff determination as the sharp downside tail.",
    "positioning_washout": "Forced-selling pressure: there is no yield-focused or passive shareholder base that would trigger a mechanical forced-selling event, and no dividend cut or strategy pivot that could set one off — Ambu pays no meaningful dividend and the investment case turns on growth, not income. The classic forced-liquidation dynamic does not apply.\n\nWhat the positioning data show instead is an already weak, conviction-light holder base rather than a coiled spring: a smart-money score of 9 out of 100 (bottom decile), institutional flow at a neutral 50 out of 100, an insider buy ratio of 0.00 (no insider purchases at a price 21% below the 200-day moving average and near the bottom of the 52-week range, where genuine value buyers would normally step in), and a tape only 11% up its 52-week range.\n\nThat combination argues against a violent capitulation flush that resets the stock cheaply — there is no crowded, wrong-way, leveraged long position to blow out. It also argues against a deep-value 'everyone has already sold' floor thesis: the absence of insider buying and the bottom-decile smart-money reading mean informed money is not accumulating into the weakness. There is no washout to wait for and no washout to buy after. The shareholder structure is simply soft, consistent with a stock continuing to de-rate from a premium multiple rather than one being mechanically liquidated to a floor.",
    "moderator_conclusion": "Pass for now, conviction 2 out of 5. Ambu is a high-quality, well-managed business — the operational turnaround is real (revenue up from DKK 4.78 billion to DKK 6.04 billion, EBIT margin before special items up from roughly 6% to 13%, net income tripled, fortress net-cash balance sheet, Altman Z-score of 9.5, and a management team that refuses to flatter its own guidance). The problem is that it is profoundly mis-labelled as a deep-value opportunity and is priced for perfection: 180.3 times trailing free cash flow, zero margin of safety, every valuation model reading negative 100% margin of safety, on a free-cash-flow base that has been flat for three years and printed just DKK 13 million last quarter. Run-rate earnings per share on a trailing-twelve-months basis is DKK 1.78, well below the DKK 2.28 headline, and the most recent quarter came in 37% below the prior year. The market is too optimistic, not too pessimistic — where we disagree with the market runs against the longs.\n\nApplying the current market regime sharpens the pass rather than rescuing it. The regime favours structural special situations in thinly covered pockets — distressed or deleveraging credits, spin-offs, forced sellers — and explicitly discounts hard-binary, macro-controlled catalysts. Ambu has no special-situation structure (no spin-off, no activist, no buyback, no asset sale; single cash-generating unit) and its only hard-dated catalysts are the binary, externally controlled Section 232 tariff ruling and the IEEPA court case, exactly the low-quality catalyst type the regime penalises. The regime also warns hard against theses whose resolution hinges on a single shared macro factor: Ambu's margin glide-path to 20% now depends on tariff and currency costs 'normalising' (management's word, despite an open court case) plus the Mexico and USMCA manufacturing ramp — a resolution driver concentrated in one policy outcome the company does not control.\n\nNone of the regime's favourable conditions apply here. Positioning confirms the caution rather than offering a washed-out entry: smart-money score 9 out of 100, insider buy ratio 0.00, price 21% below the 200-day moving average and near the bottom of its 52-week range — a de-rating premium-growth stock, not a capitulated value floor. The single genuine under-modelled positive, SureSight's roughly DKK 4 billion US video-laryngoscope market, is real but far too small to justify 180 times FCF.\n\nThis is not a value trap on the operating line (the business is sound) and it is not a short — it is a quality compounder whose price already discounts the bull case several times over, with a binary tariff headwind as the near-term swing factor. The disciplined action is to pass now and revisit only on a material de-rating toward something resembling a margin of safety, or on hard evidence that FCF conversion is inflecting toward reported earnings. Neither condition is present today. Conviction 2 (challenged on valuation, no value-unlocking catalyst, macro-binary risk, mis-labelled signal); the current regime overlay moves it down, not up.",
    "interrogator_dossier": "Ambu A/S (AMBU-B.CO) — Forensic Interrogation Dossier\n\nTranscripts analysed: first quarter fiscal year 2023/24 (30 January 2024), second quarter fiscal year 2023/24 (14 May 2024), fourth quarter fiscal year 2023/24 (6 November 2024), fourth quarter fiscal year 2024/25 (5 November 2025), first quarter fiscal year 2025/26 (4 February 2026). Financial trajectory cross-referenced from screener scan and FMP trailing-twelve-months data as of 31 March 2026. Signal type: deep value (methodology: enterprise value divided by gross profit).\n\n\nNarrative Arc\n\nAmbu is a Danish single-use (disposable) endoscopy pure-play in the middle of a multi-year operational turnaround executed under CEO Britt Meelby Jensen (in seat since mid-2022) and CFO Henrik Skak Bender (joined January 2024). Across these calls the story does not pivot — it compounds and matures, which is itself the key finding.\n\nThe opening frame (first to second quarter fiscal year 2023/24, early 2024): the 'ZOOM IN' turnaround strategy. The headline was a credibility-restoring inflection: organic growth of 14% (first quarter) then 15.5% (second quarter), EBIT margin before special items vaulting from 6% to 10% year-over-year in the first quarter and from 3.9% to 14.2% year-over-year in the second quarter. The growth engine was explicitly Endoscopy Solutions, up 25% in the first quarter and 22.3% in the second quarter, already 59-60% of revenue, while the legacy Anaesthesia and Patient Monitoring franchise was reframed as a cash-generating, price-taking segment rather than a growth driver. New product catalysts were seeded methodically: the aScope 5 Broncho (together with the CMS transitional pass-through (TPT) reimbursement designation — the only bronchoscope granted it, effective 1 January 2024, with a 24-month life and a potential 36-month extension), the aScope 5 Cysto and Uretero urology platform (CE mark in November 2023, US approval pending), and a deliberate expectation-management note that the ureteroscope launch curve spans 'six months to 12 months' and 'you should not expect any significant revenue this fiscal year.'\n\nThe middle frame (fourth quarter fiscal year 2023/24, November 2024): strategy on track, but the first honest blemishes appear. Full-year fiscal year 2023/24 delivered 13.8% revenue growth with 19.7% Endoscopy growth. But fourth-quarter organic growth decelerated to 10.6% (Endoscopy only 4.5-14.5% depending on the cut), and management took a gastrointestinal write-down on Invendo-acquired Duodeno and Colon technology and paused the cholangioscope — a quiet admission that gastroenterology 'takes longer to unlock... than what was originally assumed.' Separately, Anaesthesia and Patient Monitoring growth was now partly carried by price increases, with an explicit warning of lost exclusivity ('there can still... be some revenue lost as some customers may decide to try other products').\n\nThe current frame (fourth quarter fiscal year 2024/25 through first quarter fiscal year 2025/26, late 2025 into early 2026): the strategy was rebranded from 'ZOOM IN' to 'ZOOM AHEAD' with a Capital Markets Day on 1 October 2025 raising the long-term target to global endoscopy leadership and a 20% EBIT margin by 2028, with long-term guidance extended to fiscal year 2029/30. Full-year fiscal year 2024/25 delivered 13.1% organic growth (Endoscopy 15.4%), a 13.0% EBIT margin, and DKK 407 million of FCF. But two exogenous shocks now dominate the script that did not exist in 2024: US tariffs (Section 232 and the IEEPA court case) and currency headwinds (US dollar depreciation against the Chinese renminbi, Malaysian ringgit, and Mexican peso cost base). By the first quarter of fiscal year 2025/26 (February 2026), total growth had cooled to 8.6% (Endoscopy 14.4%, Anaesthesia and Patient Monitoring negative 0.1%), FCF had collapsed to DKK 13 million for the quarter, and the fiscal year guidance was walked back from 11-13% to 10-13% — a move analysts pushed back on hard (see Analyst Pressure Points).\n\nGrowth drivers introduced and their current status: aScope 5 Broncho (introduced strongly, still the core driver, durable); TPT reimbursement (introduced as a catalyst, repeatedly described as hard to quantify — 'difficult to exactly monitor the net effect' — effectively never converted to a hard number, now expiring within the 24-to-36-month window); urology platform (introduced, scaling but 'a fairly limited part of overall urology revenue'); SureSight video laryngoscope (introduced in fiscal year 2024/25, 'starting to generate meaningful revenue,' with a Mobile version added in the first quarter of fiscal year 2025/26 — the newest genuine catalyst); gastrointestinal (introduced with ambition, quietly demoted to 'investing more limited... will take time'); mergers and acquisitions (introduced in the second quarter of fiscal year 2023/24 as balance-sheet firepower, recurs but has never been executed).\n\n\nClaims Versus Financials — Forensic Assessment\n\nThe financials broadly corroborate the turnaround claim. This is not a company whose narrative outruns its numbers on the operating line. The divergence is on valuation, cash conversion, and forward-acceleration claims.\n\nManagement claimed strong organic revenue growth and a turnaround inflection (first to second quarter fiscal year 2023/24). Revenue went from DKK 4.78 billion in fiscal year 2023 to DKK 5.39 billion in fiscal year 2024 to DKK 6.04 billion in fiscal year 2025, a three-year compound annual growth rate of 10.8% and 12.0% growth year-over-year. Assessment: verified. Sustained double-digit organic growth is real and corroborated.\n\nManagement claimed the EBIT margin was lifting on operating leverage toward 20% by 2028 (recurring across calls). Net margin reached 10.1%; net income went from DKK 168 million to DKK 235 million to DKK 609 million across fiscal years 2023 to 2025; EPS went from DKK 0.64 to DKK 0.88 to DKK 2.28 (+159% year-over-year). EBIT margin before special items reached 13.0% in fiscal year 2025. Assessment: verified, with corrections. The DKK 609 million figure and DKK 2.28 EPS are inflated relative to the underlying run rate (see below). The margin gain from 6% to 13% over the arc is real; the next seven percentage points to reach 20% are the unproven half.\n\nManagement claimed strong free cash flow generation (first to second quarter fiscal year 2023/24 and fiscal year 2025). Actual FCF growth was negative 7.0% year-over-year; the three-year FCF compound annual growth rate was 0.0%; trailing-twelve-months FCF was DKK 610 million; the most recent quarter's EPS was down 37% year-over-year; first-quarter fiscal year 2025/26 FCF was only DKK 13 million; and the price-to-FCF ratio is 180.3 times. Assessment: did not hold up — this is the soft underbelly. FCF has been flat for three years while reported earnings grew. Cash conversion badly lags reported profit, and the most recent quarter's FCF is near zero. The 'strong FCF' framing is the least supported claim.\n\nThe fiscal year 2025 net income of DKK 609 million and EPS of DKK 2.28 were presented as reflecting earnings power (fiscal year 2025/26 reporting). However, trailing-twelve-months diluted EPS is only DKK 1.78, and the most recent quarter's EPS was down 37% year-over-year. Assessment: did not hold up in terms of quality of earnings. The fiscal year headline EPS overstates the run rate; trailing-twelve-months (DKK 1.78) and the negative 37% most-recent-quarter print indicate the DKK 2.28 includes one-off, seasonal, or currency-favourable elements that are already reversing. The appropriate run-rate figure is DKK 1.78, not DKK 2.28.\n\nManagement claimed 'solid double-digit' Endoscopy growth accelerating into fiscal year 2025/26 (fourth quarter fiscal year 2024/25 and first quarter fiscal year 2025/26). Endoscopy grew 14.4% in the first quarter of fiscal year 2025/26, but total growth decelerated from 14% to 13.8% to 13.1% to 8.6%; Anaesthesia and Patient Monitoring fell 0.1%. Assessment: partially verified. Endoscopy is genuinely double-digit; but the consolidated deceleration as Anaesthesia and Patient Monitoring rolls over is real, and the 'acceleration ahead' promise is forward-looking and unproven.\n\nManagement claimed a fortress balance sheet, a debt position approaching zero, and acquisition firepower (from the second quarter of fiscal year 2023/24 onward). Net cash is DKK 140 million (corrected from a scan figure of DKK 289 million); Altman Z-score is 9.5; Piotroski score is 6 out of 9. Assessment: verified. The balance sheet claim is the most fully corroborated. Net cash plus a Z-score of 9.5 equals genuine financial optionality. The question is whether they ever use it — they have not over two years of saying it is around the corner.\n\nManagement claimed returns were improving with the turnaround (recurring across calls). However, return on equity is 5.2% and return on invested capital is 5.9%. Assessment: did not hold up at the level. Even after the turnaround, returns on capital are below a reasonable cost of capital. The 'global leadership' ambition has not yet translated into capital-efficient returns, and a premium-multiple stock earning roughly 6% return on invested capital is a tension the calls never directly address.\n\nThe TPT and CMS reimbursement was described as a meaningful catalyst (first quarter fiscal year 2023/24 through fourth quarter fiscal year 2024/25). No isolable revenue line has ever appeared; management repeatedly offered 'difficult to exactly monitor the net effect' and 'a little difficult right now to fully estimate.' Assessment: unverifiable and soft. Raised four times, quantified zero times, now late in its 24-to-36-month life. A catalyst that never showed up in a number.\n\nBottom line of the forensic pass: the operating story is real (revenue and margin recovery plus a fortress balance sheet), but three things the bulls lean on are weaker than the narrative suggests. FCF has been flat for three years and the price-to-FCF ratio is 180 times — cash has not followed earnings. Run-rate EPS is DKK 1.78 on a trailing-twelve-months basis, not the DKK 2.28 headline, and the most recent quarter is down 37% year-over-year. And return on invested capital is roughly 6%, far below what the valuation implies.\n\n\nTone and Confidence Trajectory\n\nOverall: rising through fiscal year 2023/24, then stable but increasingly defensive by fiscal year 2025/26. There is a clear migration from offensive (growth and investment) language to defensive (tariff, currency, and cost-mitigation) language in the last two calls.\n\nFirst quarter fiscal year 2023/24 (rising, offensive): 'Off to a strong start... 14% organic revenue growth... 25% growth in our key business area.' Confident, product-led, no macro hedging. CFO transition handled smoothly.\n\nSecond quarter fiscal year 2023/24 (peak confidence): 'I'm very proud about the momentum... two years since I took over.' Raised the Endoscopy segment guidance from 'around 15%' to 'above 15%.' Pure offense — pricing power, market-share gains, research and development.\n\nFourth quarter fiscal year 2023/24 (confident but with first defensive notes): still 'strong performance... a lot of momentum,' but now fielding a write-down, a paused product, and lost-exclusivity risk in Anaesthesia and Patient Monitoring. Tone stays constructive; the content turns more two-handed.\n\nFourth quarter fiscal year 2024/25 (stable, strategically expansive but macro-shadowed): 'Very strong organic revenue growth of 13.1%'; launched the larger 'ZOOM AHEAD' ambition. But the script now introduces 'two external factors... FX and tariffs that had a negative impact,' with a repeated insistence that 'if you take the tariffs aside, we are really exactly on that journey' — a tell that the clean story now requires an asterisk.\n\nFirst quarter fiscal year 2025/26 (defensive dominates): 'Adjusting for temporarily high tariff costs... and also some FX headwind.' Whole blocks of questions and answers are now about Section 232 timing, USMCA, the Mexico manufacturing ramp percentage, and mitigation described as 'on plan, neither ahead nor behind.' The word 'temporarily' is load-bearing and repeated. Growth language is still present ('we expect an acceleration... in the coming quarters') but is now forward-promised rather than just-delivered.\n\nSpecificity over time: management became more specific on currency impact (quantifying the Danish krone effect 'for the last two quarters') and the Mexico and tariff mitigation, but consistently refused specificity on the TPT revenue impact, on unit and volume numbers ('we don't provide volume numbers... because that also caused a lot of confusion'), and on segment-level operating expense ratios. The withdrawal from volume disclosures — which they used to provide — represents a small but real reduction in transparency.\n\n\nGuidance Credibility\n\nReliability: medium-high on multi-year strategy; the recent in-year guidance walk-back is the one blemish.\n\nThe Endoscopy segment guidance for fiscal year 2023/24 was raised mid-year (from 'around 15%' to 'above 15%' in the second quarter) and delivered 19.7% — a clean over-delivery. On FCF for fiscal year 2023/24, after a strong DKK 135 million first quarter (roughly 50% of the full-year guide), the CFO explicitly declined to raise guidance, citing upcoming capital expenditure and working-capital normalisation headwinds. Fiscal year 2023/24 finished with positive FCF — a deliberately conservative, well-explained stance. This is a sandbagging-then-meeting pattern, which is credibility-positive for guidance but also explains why the screener's consensus-beat rate looks poor.\n\nOn the 20% EBIT margin by 2028 target (extended to fiscal year 2029/30): reaffirmed repeatedly and defended pointedly. When an analyst floated reporting it on an underlying basis excluding tariffs and currency, CFO Bender refused the easier framing: 'I don't see that. We guide EBIT margin, including FX... we believe... the impact... is something we can manage and still deliver on the target.' Refusing to move the goalposts is a credibility marker.\n\nThe one blemish — the in-year guidance cut: at the Capital Markets Day in November 2025 the fiscal year 2025/26 guide was effectively 11-13%; one month later it became 10-13%. Analysts pushed back twice. Management's defence — 'it's not that we are more cautious... we do see a three percentage point margin in the world that we live in' — is honest but represents a soft guide-down dressed as a wider range, landing in the same quarter FCF fell to DKK 13 million.\n\nReconciliation with the screener beat-rate (consensus beaten in one of seven quarters, 14%): the low beat-rate does not primarily reflect execution misses here — it reflects a deliberate sandbagging posture on FCF, a European reporting cadence where 'beats' are measured differently, and a fiscal year 2025 EPS figure boosted by items that do not recur. Strategic guidance has been hit or exceeded; the quarterly consensus relationship is noisy. Net: guidance reliability is genuinely medium-high, with the caveat that the trajectory of guidance is now flattening or declining at the margin rather than rising.\n\n\nAnalyst Pressure Points\n\nRecurring questions management deflected or could not fully answer — and where the analyst instinct proved prescient:\n\nFirst, free cash flow sustainability (Yiwei Zhou, first quarter fiscal year 2023/24): 'Is there any cost headwind for you to generate less free cash flow?' The CFO flagged capital expenditure and working-capital normalisation. Prescient — FCF is now flat over three years and DKK 13 million in the most recent quarter. Analysts identified the cash-conversion problem early; it has materialised.\n\nSecond, TPT and CMS revenue impact (multiple quarters, Niels Granholm-Leth and Yiwei Zhou): repeatedly asked to quantify; management repeatedly could not. A two-year unanswered question on a headline catalyst.\n\nThird, the in-year guidance cut (Yiwei Zhou, fourth quarter fiscal year 2024/25): asked twice why 11-13% became 10-13% one month after the Capital Markets Day. Management's non-specific response did not satisfy the questioner.\n\nFourth, competition encroachment (Niels Granholm-Leth, recurring): 'Almost not a month goes by without a new player.' Management's reframe — that competition helps drive conversion from reusable scopes and is 'not necessarily only a negative' — is a reframe rather than a rebuttal. Boston Scientific (urology and ureteroscopy leader), Chinese players (Pewson), and Olympus's single-use entry are all named threats in categories Ambu claims as its own.\n\nFifth, the gastrointestinal write-down accounting (Niels Granholm-Leth, fourth quarter fiscal year 2023/24): a sharp question on whether goodwill rather than technology should have been impaired, and pointing out that the impairment flatters the future EBIT margin by roughly 0.5 percentage points. Management conceded the mechanical margin benefit — a subtle distinction between margin earned through operations and margin aided by accounting that the bull case must net out.\n\nSixth, tariff and Section 232 timing (Jesper Ingildsen and Martin Brenoe, first quarter fiscal year 2025/26): heavy questioning on a binary, externally controlled outcome ('likely it will come out in the next month or maybe two'); USMCA dependency; the Mexico ramp. Management is preparing scenarios but the outcome is not in their control — a live near-term overhang.\n\nThe overarching analyst concern management is not fully addressing: the gap between reported EPS growth and flat FCF; whether the 20% margin target survives a structurally higher tariff and currency regime without leaning on the gastrointestinal write-down margin tailwind; and why a balance sheet described for two years as carrying acquisition firepower has produced no deal.\n\n\nPositive and Negative Signals\n\nPositive signals:\n\nDurable double-digit organic Endoscopy growth is corroborated by the financials (revenue DKK 4.78 billion to DKK 6.04 billion; Endoscopy up 19.7% in fiscal year 2024 and 15.4% in fiscal year 2025). The core engine is real.\n\nGenuine margin turnaround: EBIT before special items moved from 6% to 13% over the arc; net income went from DKK 168 million to DKK 609 million; the operating-leverage thesis has partly delivered.\n\nFortress balance sheet: net cash (DKK 140 million), Altman Z-score 9.5, gross margin stable at 56%. Financial survivability is not in question.\n\nManagement discipline on guidance integrity: refused to raise FCF on a strong first quarter; refused to strip out currency from the margin target. CFO Bender consistently says no to easy outs.\n\nA live new catalyst in SureSight and SureSight Mobile: a video laryngoscope into a roughly DKK 4 billion US market, 50% of US intubations now video and growing around 20%, 'starting to generate meaningful revenue' in the first quarter of fiscal year 2025/26 — the freshest, most quantified opportunity in the deck.\n\nNegative signals:\n\n180 times price-to-FCF on three years of flat FCF. The three-year FCF compound annual growth rate is 0.0%, FCF fell 7% year-over-year, first-quarter fiscal year 2025/26 FCF was DKK 13 million — yet the multiple prices hyper-growth. This is a growth-and-quality valuation, the opposite of a deep-value label.\n\nRun-rate EPS is DKK 1.78 on a trailing-twelve-months basis, not the DKK 2.28 fiscal year headline; the most recent quarter's EPS was down 37% year-over-year. Reported earnings-power optics are inflated by non-recurring or seasonal or currency-favourable items that are already reversing.\n\nReturn on invested capital roughly 5.9% and return on equity 5.2% — below a reasonable cost of capital, funding a premium multiple and a 'global leadership' ambition.\n\nIn-year guidance walk-back (11-13% to 10-13%) one month after the Capital Markets Day, in the same quarter FCF collapsed — the first time the trajectory of guidance turned downward.\n\nTariff and currency headwinds are now structural, not temporary. Management calls them temporary, but Section 232 is unresolved, the IEEPA court case is open, and currency is a standing cost-base mismatch. The path to 20% EBIT margin depends on the Mexico ramp and mitigation described as 'on plan.'\n\nGastrointestinal leg demoted (Invendo write-down, cholangioscope paused, 'takes longer to unlock') — a real contraction of the original total addressable market story, partly masked by the margin tailwind the write-down created.\n\nSmart-money score 9 out of 100, insider buy ratio 0.00, price 21% below the 200-day moving average, and only 11% up the 52-week range. No insider conviction, weak institutional flow, and a tape in a clear downtrend — positioning corroborates the bears, not a deep-value floor.\n\n\nHidden Signals\n\nThe rebrand as a tell: 'ZOOM IN' (turnaround) became 'ZOOM AHEAD' and 'next-era' (growth leadership). Renaming the strategy at exactly the point the easy turnaround gains (margin 6% to 13%) have been banked and the hard gains (to 20%) remain is a classic narrative refresh to sustain the multiple as organic growth decelerates from 14% to 8.6%.\n\n'Temporarily' as a load-bearing word: 'temporarily high tariff costs' appears repeatedly. The persistence of the qualifier across two quarters, paired with an open court case and unresolved Section 232 proceedings, suggests management needs the market to treat a possibly structural cost as transitory.\n\nDisclosure narrowing: management stopped providing unit and volume numbers ('caused a lot of confusion') and will not give segment-level operating expense ratios. Less granularity is appearing exactly as growth moderates.\n\nCompetition language softening into reframe: early calls named competitors as manageable; by fiscal year 2024/25 the framing is that competition is helpful because it accelerates conversion from reusable scopes. True at the category level, but this is also how a first-mover rationalises losing ground it can no longer claim alone — Boston Scientific, Olympus, and Chinese entrants across pulmonology, urology, ENT, and ureteroscopy are all now active.\n\nMergers and acquisitions as a permanent option never exercised: 'firepower... around the corner... nothing waiting to announce' recurs from the second quarter of fiscal year 2023/24 onward with zero execution across two years. Either capital discipline or an inability to find accretive targets at sensible prices — increasingly the latter as a narrative crutch.\n\nNew US commercial leader (Scott Heinzelman, August 2025) and restructuring of the US field force toward integrated delivery networks and group purchasing organisations — an admission that the world's largest market needed an organisational fix; this carries execution cost and disruption risk in exactly the current quarters.\n\nThe CFO is the credibility anchor. Henrik Skak Bender (from January 2024) is consistently the one who refuses the flattering framing — no FCF raise, no ex-currency margin reporting. New-CFO conservatism is doing real work in keeping this deck honest.\n\n\nCapital-Allocation Verdict\n\nClassification: stable, with a maturing and decelerating bias — a successful turnaround transitioning into a harder, slower-compounding, externally-shocked second act.\n\nThis is not a deteriorating story and it is not a value trap on the operating line. The turnaround is real, the balance sheet is a fortress, and a genuine new catalyst in SureSight exists. But it is also not what the deep-value label implies: there is no margin of safety (180 times trailing FCF, DCF fair value roughly DKK 4.90 against a price of DKK 66, every model reading negative 100% margin of safety), FCF has been flat for three years, run-rate EPS is below the headline, return on invested capital is roughly 6%, and the stock is in a downtrend 21% below the 200-day moving average with zero insider buying and a bottom-decile smart-money score. The classification is 'stable' because the business is stable-to-good; the security is priced for perfection and is in the middle of a de-rating.\n\nManagement credibility 4 out of 5; trajectory stable.\n\nThe single most important consideration before sizing: the valuation versus cash-conversion gap. You are being asked to pay 180 times FCF for a company whose FCF has not grown in three years and whose most recent quarter produced DKK 13 million of it, on the promise of a margin expansion to 20% by 2028 that must now survive a structurally higher tariff and currency regime. The operating quality is real; the price embeds an acceleration the cash flows have not shown and that the most recent quarter — 8.6% growth, near-zero FCF, guidance cut, EPS down 37% year-over-year — actively contradicts. Add only against a clean re-rating lower or hard evidence that FCF conversion is inflecting toward reported earnings, not against the turnaround narrative, which is already priced in several times over.",
    "engine": "opus-4.8-regime",
    "voiced": true
  }
]